flask_telegram.py
flask_telegram_gaemail.py
setup.py
flask_telegram.egg-info/PKG-INFO
flask_telegram.egg-info/SOURCES.txt
flask_telegram.egg-info/dependency_links.txt
flask_telegram.egg-info/not-zip-safe
flask_telegram.egg-info/requires.txt
flask_telegram.egg-info/top_level.txt