Metadata-Version: 1.1
Name: flask-telegram
Version: 0.0.1
Summary: 
